aidge_backend_opencv-0.2.0.dist-info/RECORD
aidge_backend_opencv-0.2.0.dist-info/top_level.txt
aidge_backend_opencv-0.2.0.dist-info/METADATA
aidge_backend_opencv-0.2.0.dist-info/WHEEL
aidge_backend_opencv-0.2.0.dist-info/licenses/LICENSE
aidge_backend_opencv.libs/libopencv_imgcodecs-4f85778d.so.4.9.0
aidge_backend_opencv.libs/libopencv_features2d-0e49ee46.so.4.9.0
aidge_backend_opencv.libs/libopencv_photo-ec6d3ea3.so.4.9.0
aidge_backend_opencv.libs/libopencv_dnn-953caa54.so.4.9.0
aidge_backend_opencv.libs/libopencv_core-0285646b.so.4.9.0
aidge_backend_opencv.libs/libopencv_ml-58ec7db1.so.4.9.0
aidge_backend_opencv.libs/libopencv_video-834ee753.so.4.9.0
aidge_backend_opencv.libs/libopencv_imgproc-0cdd7eff.so.4.9.0
aidge_backend_opencv.libs/libgomp-a34b3233.so.1.0.0
aidge_backend_opencv.libs/libopencv_flann-fb5c0475.so.4.9.0
aidge_backend_opencv/__init__.py
aidge_backend_opencv/aidge_backend_opencv.cpython-313-x86_64-linux-gnu.so
