Metadata-Version: 2.4
Name: aidge_backend_opencv
Version: 0.2.0
Summary: Opencv implementations of the operators and tensor of aidge framework
License: Eclipse Public License - v 2.0
Project-URL: Homepage, https://www.deepgreen.ai/en/platform
Project-URL: Documentation, https://eclipse.dev/aidge/
Project-URL: Repository, https://gitlab.eclipse.org/eclipse/aidge/aidge_backend_opencv
Project-URL: Issues, https://gitlab.eclipse.org/eclipse/aidge/aidge_backend_opencv/-/issues/
Project-URL: Changelog, https://gitlab.eclipse.org/eclipse/aidge/aidge_backend_opencv/-/releases
Classifier: Development Status :: 2 - Pre-Alpha
Classifier: Programming Language :: Python :: 3
Requires-Python: >=3.10
License-File: LICENSE
Requires-Dist: numpy>=1.21.6
Dynamic: license-file
